clovers_aichat/__init__.py
clovers_aichat/ai/gemini.py
clovers_aichat/ai/hunyuan.py
clovers_aichat/ai/mix.py
clovers_aichat/ai/openai.py
clovers_aichat/clovers.py
clovers_aichat/config.py
clovers_aichat/core.py
clovers_aichat/manager.py
clovers_aichat-1.1.0.dist-info/LICENSE
clovers_aichat-1.1.0.dist-info/METADATA
clovers_aichat-1.1.0.dist-info/WHEEL
clovers_aichat-1.1.0.dist-info/RECORD
